Workbook

Sheet Painel
A1: Painel da confeitaria
A3: Faturamento (todas as vendas) | B3: =SUM(Vendas!F:F)
A4: Número de vendas | B4: =COUNTA(Vendas!A2:A500)
A5: Ticket médio | B5: =B3/B4
A6: Lucro de outubro | B6: =Caixa!D5
A7: Itens para repor | B7: =COUNTIF(Estoque!E:E,"Repor")
A8: Clientes sumidos | B8: =COUNTIF(Clientes!E:E,"Sumido")

Sheet Vendas
A1: Data | B1: Cliente | C1: Produto | D1: Qtd | E1: Preço | F1: Total
A2: 46254 | B2: Marcos Reis | C2: Bolo de pote | D2: 3 | E2: =VLOOKUP(C2,Produtos!A:B,2,FALSE) | F2: =D2*E2
A3: 46255 | B3: Marcos Reis | C3: Torta de limão | D3: 2 | E3: =VLOOKUP(C3,Produtos!A:B,2,FALSE) | F3: =D3*E3
A4: 46256 | B4: Marcos Reis | C4: Bolo de pote | D4: 3 | E4: =VLOOKUP(C4,Produtos!A:B,2,FALSE) | F4: =D4*E4
A5: 46296 | B5: Carlos Lima | C5: Salgado (cento) | D5: 1 | E5: =VLOOKUP(C5,Produtos!A:B,2,FALSE) | F5: =D5*E5
A6: 46296 | B6: João Pedro | C6: Bolo de pote | D6: 2 | E6: =VLOOKUP(C6,Produtos!A:B,2,FALSE) | F6: =D6*E6
A7: 46297 | B7: Lucas Martins | C7: Bolo de pote | D7: 5 | E7: =VLOOKUP(C7,Produtos!A:B,2,FALSE) | F7: =D7*E7
A8: 46297 | B8: Rita Alves | C8: Bolo de pote | D8: 10 | E8: =VLOOKUP(C8,Produtos!A:B,2,FALSE) | F8: =D8*E8
A9: 46298 | B9: Rita Alves | C9: Torta de limão | D9: 3 | E9: =VLOOKUP(C9,Produtos!A:B,2,FALSE) | F9: =D9*E9
A10: 46298 | B10: Carlos Lima | C10: Torta de limão | D10: 2 | E10: =VLOOKUP(C10,Produtos!A:B,2,FALSE) | F10: =D10*E10
A11: 46299 | B11: Ana Souza | C11: Brigadeiro (cento) | D11: 2 | E11: =VLOOKUP(C11,Produtos!A:B,2,FALSE) | F11: =D11*E11
A12: 46299 | B12: Lucas Martins | C12: Bolo de pote | D12: 7 | E12: =VLOOKUP(C12,Produtos!A:B,2,FALSE) | F12: =D12*E12
A13: 46299 | B13: Lucas Martins | C13: Bolo de pote | D13: 7 | E13: =VLOOKUP(C13,Produtos!A:B,2,FALSE) | F13: =D13*E13
... A65: 46323 | B65: Fernanda Costa | C65: Salgado (cento) | D65: 1 | E65: =VLOOKUP(C65,Produtos!A:B,2,FALSE) | F65: =D65*E65

Sheet Produtos
A1: Produto | B1: Preço | C1: Unidade | D1: Vendido no mês
A2: Bolo de pote | B2: 12 | C2: unidade | D2: =SUMIFS(Vendas!F:F,Vendas!C:C,A2)
A3: Brigadeiro (cento) | B3: 110 | C3: cento | D3: =SUMIFS(Vendas!F:F,Vendas!C:C,A3)
A4: Brownie | B4: 8 | C4: unidade | D4: =SUMIFS(Vendas!F:F,Vendas!C:C,A4)
A5: Torta de limão | B5: 85 | C5: inteira | D5: =SUMIFS(Vendas!F:F,Vendas!C:C,A5)
A6: Salgado (cento) | B6: 90 | C6: cento | D6: =SUMIFS(Vendas!F:F,Vendas!C:C,A6)
A7: Bolo de aniversário | B7: 160 | C7: inteiro | D7: =SUMIFS(Vendas!F:F,Vendas!C:C,A7)

Sheet Estoque
A1: Item | B1: Quantidade | C1: Mínimo | D1: Alerta | E1: Situação
A2: Farinha (kg) | B2: 6 | C2: 2 | D2: =C2*1.5 | E2: =IF(B2<C2,"Repor",IF(B2<D2,"Atenção","OK"))
A3: Chocolate (kg) | B3: 2 | C3: 1.5 | D3: =C3*1.5 | E3: =IF(B3<C3,"Repor",IF(B3<D3,"Atenção","OK"))
A4: Açúcar (kg) | B4: 5 | C4: 2 | D4: =C4*1.5 | E4: =IF(B4<C4,"Repor",IF(B4<D4,"Atenção","OK"))
A5: Leite condensado (latas) | B5: 4 | C5: 6 | D5: =C5*1.5 | E5: =IF(B5<C5,"Repor",IF(B5<D5,"Atenção","OK"))
A6: Embalagens (un) | B6: 30 | C6: 15 | D6: =C6*1.5 | E6: =IF(B6<C6,"Repor",IF(B6<D6,"Atenção","OK"))

Sheet Clientes
A1: Nome | B1: Telefone | C1: Última compra | D1: Total gasto | E1: Situação
A2: Ana Souza | B2: (95) 99123-4567 | C2: =_xlfn.MAXIFS(Vendas!A:A,Vendas!B:B,A2) | D2: =SUMIFS(Vendas!F:F,Vendas!B:B,A2) | E2: =IF(C2=0,"Novo",IF(TODAY()-C2>30,"Sumido","Ativo"))
A3: Carlos Lima | B3: (95) 98114-2290 | C3: =_xlfn.MAXIFS(Vendas!A:A,Vendas!B:B,A3) | D3: =SUMIFS(Vendas!F:F,Vendas!B:B,A3) | E3: =IF(C3=0,"Novo",IF(TODAY()-C3>30,"Sumido","Ativo"))
A4: Rita Alves | B4: (95) 99207-5518 | C4: =_xlfn.MAXIFS(Vendas!A:A,Vendas!B:B,A4) | D4: =SUMIFS(Vendas!F:F,Vendas!B:B,A4) | E4: =IF(C4=0,"Novo",IF(TODAY()-C4>30,"Sumido","Ativo"))
A5: João Pedro | B5: (95) 99876-1034 | C5: =_xlfn.MAXIFS(Vendas!A:A,Vendas!B:B,A5) | D5: =SUMIFS(Vendas!F:F,Vendas!B:B,A5) | E5: =IF(C5=0,"Novo",IF(TODAY()-C5>30,"Sumido","Ativo"))
A6: Beatriz Nunes | B6: (95) 98450-7712 | C6: =_xlfn.MAXIFS(Vendas!A:A,Vendas!B:B,A6) | D6: =SUMIFS(Vendas!F:F,Vendas!B:B,A6) | E6: =IF(C6=0,"Novo",IF(TODAY()-C6>30,"Sumido","Ativo"))
A7: Marcos Reis | B7: (95) 99311-0087 | C7: =_xlfn.MAXIFS(Vendas!A:A,Vendas!B:B,A7) | D7: =SUMIFS(Vendas!F:F,Vendas!B:B,A7) | E7: =IF(C7=0,"Novo",IF(TODAY()-C7>30,"Sumido","Ativo"))
A8: Fernanda Costa | B8: (95) 99102-3344 | C8: =_xlfn.MAXIFS(Vendas!A:A,Vendas!B:B,A8) | D8: =SUMIFS(Vendas!F:F,Vendas!B:B,A8) | E8: =IF(C8=0,"Novo",IF(TODAY()-C8>30,"Sumido","Ativo"))
A9: Lucas Martins | B9: (95) 98877-6655 | C9: =_xlfn.MAXIFS(Vendas!A:A,Vendas!B:B,A9) | D9: =SUMIFS(Vendas!F:F,Vendas!B:B,A9) | E9: =IF(C9=0,"Novo",IF(TODAY()-C9>30,"Sumido","Ativo"))

Sheet Caixa
A1: Mês | B1: Entradas | C1: Saídas | D1: Saldo | E1: Acumulado
A2: julho | B2: 5200 | C2: 3600 | D2: =B2-C2 | E2: =D2
A3: agosto | B3: 5600 | C3: 3700 | D3: =B3-C3 | E3: =E2+D3
A4: setembro | B4: 5800 | C4: 3750 | D4: =B4-C4 | E4: =E3+D4
A5: outubro | B5: =SUM(Vendas!F:F) | C5: 3780 | D5: =B5-C5 | E5: =E4+D5
